CHANGES.txt
LICENSE
MANIFEST.in
README.rst
setup.py
django_socialnetwork.egg-info/PKG-INFO
django_socialnetwork.egg-info/SOURCES.txt
django_socialnetwork.egg-info/dependency_links.txt
django_socialnetwork.egg-info/requires.txt
django_socialnetwork.egg-info/top_level.txt
socialnetwork/__init__.py
socialnetwork/signals.py
socialnetwork/urls.py
socialnetwork/base/__init__.py
socialnetwork/base/backends.py
socialnetwork/base/clients.py
socialnetwork/base/models.py
socialnetwork/base/views.py
socialnetwork/facebook/__init__.py
socialnetwork/facebook/backends.py
socialnetwork/facebook/clients.py
socialnetwork/facebook/models.py
socialnetwork/facebook/settings.py
socialnetwork/facebook/urls.py
socialnetwork/facebook/views.py
socialnetwork/facebook/templates/login/login_button.html
socialnetwork/facebook/templates/share/share_button.html
socialnetwork/facebook/templatetags/__init__.py
socialnetwork/facebook/templatetags/facebook.py
socialnetwork/locale/es/LC_MESSAGES/django.mo
socialnetwork/locale/es/LC_MESSAGES/django.po