Metadata-Version: 1.1
Name: django-socialnetwork
Version: 0.0.6
Summary: Provides functionality to login and share with social networks to Django.
Home-page: https://github.com/gGonz/django-socialnetwork
Author: Gabriel González
Author-email: zurg.cei@gmail.com
License: Apache License (2.0)
Platform: UNKNOWN
Classifier: Development Status :: 2 - Pre-Alpha
Classifier: Intended Audience :: Developers
Classifier: License :: OSI Approved :: Apache Software License
Classifier: Environment :: Web Environment
Classifier: Operating System :: OS Independent
Classifier: Programming Language :: Python
Classifier: Framework :: Django
Classifier: Topic :: Software Development :: Libraries :: Python Modules
Classifier: Topic :: Internet
